{
	"mesh": "",
	"output": "",

	"discr_order": 1,
	"use_spline": false,

	"problem": "GenericTensor",
	"tensor_formulation":"NeoHookean",
	"export": {},
	"solver_type": "AMGCL",
	"solver_params": {"conv_tol": 1e-8,"block_size": 3,"max_iter": 5000},
	"count_flipped_els": true,
	"n_refs": 0,

	"normalize_mesh": false,
	"params": {
		"E": 210000,
		"nu": 0.3
	},

	"problem_params": {

		"dirichlet_boundary": [
			{
				"id": 5,
				"value": [
					0.0,
					0.0,
					0.0
				]
			}
		],
		"neumann_boundary": [
			{
				"id": 6,
				"value": [
					0.0,
					2.1,
					0.0
				]
			}
		]
	}

}
